examplepy/__init__.py
examplepy/module1.py
goty-0.1.0.dist-info/LICENSE
goty-0.1.0.dist-info/METADATA
goty-0.1.0.dist-info/WHEEL
goty-0.1.0.dist-info/top_level.txt
goty-0.1.0.dist-info/RECORD
